bostas/__init__.py
bostas/instabot.py
bostas-0.0.2.dist-info/LICENSE
bostas-0.0.2.dist-info/METADATA
bostas-0.0.2.dist-info/WHEEL
bostas-0.0.2.dist-info/top_level.txt
bostas-0.0.2.dist-info/RECORD
