Metadata-Version: 2.1
Name: bostas
Version: 0.0.2
Summary: Tool for social media automation
Home-page: https://github.com/tirtharajsinha/bostas/
Author: Tirtharaj Sinha
Author-email: sinhatirtharaj@gmail.com
License: UNKNOWN
Project-URL: Bug Tracker, https://github.com/tirtharajsinha/bostas/issues
Project-URL: Quick StarterPlate, https://github.com/tirtharajsinha/bostas/docu/guide.html/
Keywords: bostas python social-Media instagram automation marketing promotion bot selenium
Platform: UNKNOWN
Classifier: Programming Language :: Python :: 3
Classifier: License :: OSI Approved :: MIT License
Classifier: Operating System :: OS Independent
Classifier: Intended Audience :: End Users/Desktop
Classifier: Intended Audience :: Developers
Classifier: Topic :: Utilities
Classifier: Natural Language :: English
Classifier: Topic :: Software Development :: Build Tools
Requires-Python: >=3.6
Requires-Dist: beautifulsoup4 (==4.9.3)
Requires-Dist: requests (==2.25.1)
Requires-Dist: selenium (==3.141.0)
